wait_for_utils/__init__.py
wait_for_utils/base.py
wait_for_utils/cli.py
wait_for_utils/config.py
wait_for_utils/utils.py
wait_for_utils/wait_for_pg.py
wait_for_utils-0.1.0.dist-info/entry_points.txt
wait_for_utils-0.1.0.dist-info/LICENSE
wait_for_utils-0.1.0.dist-info/WHEEL
wait_for_utils-0.1.0.dist-info/METADATA
wait_for_utils-0.1.0.dist-info/RECORD
