Metadata-Version: 2.1
Name: wait-for-utils
Version: 0.1.0
Summary: Wait for PostgreSQL to be available before startup docker container.
Home-page: https://github.com/mtizima/wait-for-utils
License: MIT
Keywords: docker,building
Author: Dmitry
Author-email: mtizima@gmail.com
Requires-Python: >=3.7,<4.0
Classifier: License :: OSI Approved :: MIT License
Classifier: Operating System :: POSIX
Classifier: Programming Language :: Python :: 3
Classifier: Programming Language :: Python :: 3.7
Classifier: Programming Language :: Python :: 3.8
Classifier: Programming Language :: Python :: 3.9
Classifier: Topic :: Software Development :: Build Tools
Classifier: Topic :: Utilities
Requires-Dist: click (>=7.1.2,<8.0.0)
Requires-Dist: psycopg2 (>=2.8.6,<3.0.0)
Project-URL: Documentation, https://github.com/mtizima/wait-for-utils/blob/main/README.md
